Workbook

Sheet Dashboard
B1: UGC CREATOR BUSINESS OS
B2: Your brand-deal command center — pipeline, pricing, invoices, and content in one place.
B4: ACTIVE PIPELINE VALUE | D4: REVENUE — THIS MONTH | F4: REVENUE — THIS QUARTER
B5: =SUMPRODUCT((('Brand Deal Pipeline'!$E$4:$E$103="Lead")+('Brand Deal Pipeline'!$E$4:$E$103="Pitched")+('Brand Deal Pipeline'!$E$4:$E$103="Negotiating")+('Brand Deal Pipeline'!$E$4:$E$103="Contract Sent"))*('Brand Deal Pipeline'!$I$4:$I$103)) | D5: =SUMIFS(Invoices!$E$4:$E$103,Invoices!$F$4:$F$103,"Paid",Invoices!$I$4:$I$103,">="&$B$31,Invoices!$I$4:$I$103,"<="&$C$31) | F5: =SUMIFS(Invoices!$E$4:$E$103,Invoices!$F$4:$F$103,"Paid",Invoices!$I$4:$I$103,">="&$B$32,Invoices!$I$4:$I$103,"<="&$C$32)
B8: REVENUE — THIS YEAR | D8: ACTIVE DEALS | F8: WIN RATE
B9: =SUMIFS(Invoices!$E$4:$E$103,Invoices!$F$4:$F$103,"Paid",Invoices!$I$4:$I$103,">="&$B$33,Invoices!$I$4:$I$103,"<="&$C$33) | D9: =SUMPRODUCT((('Brand Deal Pipeline'!$E$4:$E$103="Lead")+('Brand Deal Pipeline'!$E$4:$E$103="Pitched")+('Brand Deal Pipeline'!$E$4:$E$103="Negotiating")+('Brand Deal Pipeline'!$E$4:$E$103="Contract Sent"))*1) | F9: =IFERROR(COUNTIF('Brand Deal Pipeline'!$E$4:$E$103,"Closed-Won")/(COUNTIF('Brand Deal Pipeline'!$E$4:$E$103,"Closed-Won")+COUNTIF('Brand Deal Pipeline'!$E$4:$E$103,"Closed-Lost")),0)
B12: AVG DEAL SIZE (CLOSED-WON) | D12: TOTAL UNPAID INVOICES | F12: TOTAL PAID INVOICES
B13: =IFERROR(AVERAGEIF('Brand Deal Pipeline'!$E$4:$E$103,"Closed-Won",'Brand Deal Pipeline'!$I$4:$I$103),0) | D13: =SUMIF(Invoices!$F$4:$F$103,"Unpaid",Invoices!$E$4:$E$103) | F13: =SUMIF(Invoices!$F$4:$F$103,"Paid",Invoices!$E$4:$E$103)
B16: How to use this workbook
B17: 1. Brand Deal Pipeline — log every brand conversation the moment it starts, even a cold DM.
B18: 2. Rate Calculator — use it BEFORE you quote a brand. Never quote off the top of your head.
B19: 3. Invoices — every deal that closes gets an invoice row, so revenue here stays real.
B20: 4. Content Calendar — plan filming/editing/posting per deal so nothing misses a deadline.
B21: 5. Usage Rights Cheat Sheet — read this once. It's the #1 place new UGC creators lose money.
B29: Internal helper cells — power the date formulas above. Don't delete.
A30: Range | B30: Start | C30: End
A31: Month | B31: =DATE(YEAR(TODAY()),MONTH(TODAY()),1) | C31: =EOMONTH(B31,0)
A32: Quarter | B32: =DATE(YEAR(TODAY()),(ROUNDUP(MONTH(TODAY())/3,0)*3)-2,1) | C32: =EOMONTH(B32,2)
A33: Year | B33: =DATE(YEAR(TODAY()),1,1) | C33: =DATE(YEAR(TODAY()),12,31)

Sheet Brand Deal Pipeline
A1: BRAND DEAL PIPELINE
A2: Log every deal the moment it starts. Row 3 is an example — overwrite it.
A3: Brand Name | B3: Contact Name | C3: Contact Email | D3: Deliverable Type | E3: Stage | F3: Rate Quoted | G3: Usage Rights | H3: Usage Fee Add-on | I3: Total Deal Value | J3: Deadline | K3: Notes
A4: Glow Skincare Co. | B4: Maria Lopez | C4: maria@glowskincare.com | D4: Video | E4: Negotiating | F4: 250 | G4: Whitelisted 30 Days | H4: 62.5 | I4: =F4+H4 | J4: 2026-09-15 | K4: Wants 2 revisions included
I5: =F5+H5
I6: =F6+H6
I7: =F7+H7
I8: =F8+H8
I9: =F9+H9
I10: =F10+H10
I11: =F11+H11
I12: =F12+H12
I13: =F13+H13
I14: =F14+H14
I15: =F15+H15
I16: =F16+H16
... I103: =F103+H103

Sheet Rate Calculator
A1: RATE CALCULATOR
A2: Use this BEFORE you quote a brand. Never price off the top of your head.
A4: STEP 1 — Your base hourly-equivalent rate
A5: Base rate ($/hour) | B5: 50 | D5: ← edit this. Blue cells are yours to change.
A7: STEP 2 — Estimated hours per deliverable (edit to match your speed)
A8: Deliverable Type | B8: Est. Hours
A9: Video | B9: 3
A10: Photo | B10: 1
A11: Video+Photo Bundle | B11: 4
A12: UGC Ad Script | B12: 2
A13: Whitelisted Content | B13: 3
A15: STEP 3 — Usage rights multiplier (edit if your market is different)
A16: Usage Rights | B16: Multiplier
A17: Organic Only | B17: 1
A18: Whitelisted 30 Days | B18: 1.25
A19: Whitelisted 90 Days | B19: 1.5
A20: Paid Ads/Whitelisted 6mo | B20: 2
A21: Full Buyout | B21: 3
A23: CALCULATE YOUR RATE
A24: Deliverable Type | B24: Video
A25: Usage Rights | B25: Organic Only
A27: Matched hours (from Step 2) | B27: =INDEX($B$9:$B$13,MATCH($B$24,$A$9:$A$13,0))
A28: Base deliverable price (rate x hours) | B28: =$B$5*$B$27 | D28: =Base Rate x Hours
A29: Matched multiplier (from Step 3) | B29: =INDEX($B$17:$B$21,MATCH($B$25,$A$17:$A$21,0))
A30: SUGGESTED RATE | B30: =ROUND($B$28*$B$29,0) | D30: =Base Deliverable Price x Multiplier. This is your floor, not your ceiling — negotiate up.

Sheet Invoices
A1: INVOICES
A2: Every closed deal gets a row here — this is what powers the Dashboard revenue numbers.
A3: Invoice # | B3: Brand Name | C3: Date Issued | D3: Due Date | E3: Amount | F3: Status | G3: Auto-Flag | H3: Payment Method | I3: Date Paid
A4: INV-0001 | B4: Glow Skincare Co. | C4: 2026-08-01 | D4: 2026-08-15 | E4: 312.5 | F4: Paid | G4: =IF(AND(F4<>"Paid",F4<>"",TODAY()>D4),"⚠ PAST DUE","") | H4: PayPal | I4: 2026-08-10
G5: =IF(AND(F5<>"Paid",F5<>"",TODAY()>D5),"⚠ PAST DUE","")
G6: =IF(AND(F6<>"Paid",F6<>"",TODAY()>D6),"⚠ PAST DUE","")
G7: =IF(AND(F7<>"Paid",F7<>"",TODAY()>D7),"⚠ PAST DUE","")
G8: =IF(AND(F8<>"Paid",F8<>"",TODAY()>D8),"⚠ PAST DUE","")
G9: =IF(AND(F9<>"Paid",F9<>"",TODAY()>D9),"⚠ PAST DUE","")
G10: =IF(AND(F10<>"Paid",F10<>"",TODAY()>D10),"⚠ PAST DUE","")
G11: =IF(AND(F11<>"Paid",F11<>"",TODAY()>D11),"⚠ PAST DUE","")
G12: =IF(AND(F12<>"Paid",F12<>"",TODAY()>D12),"⚠ PAST DUE","")
G13: =IF(AND(F13<>"Paid",F13<>"",TODAY()>D13),"⚠ PAST DUE","")
G14: =IF(AND(F14<>"Paid",F14<>"",TODAY()>D14),"⚠ PAST DUE","")
G15: =IF(AND(F15<>"Paid",F15<>"",TODAY()>D15),"⚠ PAST DUE","")
G16: =IF(AND(F16<>"Paid",F16<>"",TODAY()>D16),"⚠ PAST DUE","")
... G103: =IF(AND(F103<>"Paid",F103<>"",TODAY()>D103),"⚠ PAST DUE","")
B105: TOTAL PAID | E105: =SUMIF(F4:F103,"Paid",E4:E103)
B106: TOTAL UNPAID | E106: =SUMIF(F4:F103,"Unpaid",E4:E103)

Sheet Content Calendar
A1: CONTENT CALENDAR
A2: Plan filming, editing, and posting per deal so nothing misses a deadline.
A3: Date | B3: Brand/Deal | C3: Content Type | D3: Platform | E3: Status | F3: Caption/Notes
A4: 2026-09-10 | B4: Glow Skincare Co. | C4: Video | D4: TikTok | E4: Filming | F4: Morning routine hook, show product 0:03

Sheet Usage Rights Cheat Sheet
A1: USAGE RIGHTS CHEAT SHEET
A2: Read this once. It's the #1 place new UGC creators leave money on the table.
A3: Tier | B3: What It Actually Means | C3: Price Multiplier | D3: Use It When
A4: Organic Only | B4: Brand only gets the raw file(s). They post nothing as an ad, and don't run it through your handle or theirs as paid media. | C4: 1.0x | D4: They only want content for their own organic/unpaid social pages.
A5: Whitelisted 30 Days | B5: Brand runs your content as a paid ad THROUGH YOUR HANDLE (Spark Ads / Partnership Ads) for up to 30 days. | C5: 1.25x | D5: A short test campaign or one-off promo.
A6: Whitelisted 90 Days | B6: Same as above, for up to 90 days — the most common ask for a standard campaign flight. | C6: 1.5x | D6: A normal-length paid campaign.
A7: Paid Ads / Whitelisted 6mo | B7: Extended paid-media usage, sometimes across the brand's own channels too, for up to 6 months. | C7: 2.0x | D7: An always-on or longer-running paid campaign.
A8: Full Buyout | B8: Brand owns unlimited, perpetual usage — ads, packaging, website, anywhere, forever. | C8: 3.0x (floor) | D8: Anytime 'forever' or 'unlimited' is mentioned. Never accept 1x for this.
A10: Rule of thumb: if you don't know the brand's usage plan, ASK before you quote. Usage rights — not the content itself — is where creators leave the most money on the table.
